robotsparsetools/__init__.py
robotsparsetools/__main__.py
robotsparsetools/lib/__init__.py
robotsparsetools/lib/error.py
robotsparsetools/lib/make.py
robotsparsetools/lib/parse.py
robotsparsetools-1.3.3.dist-info/LICENSE
robotsparsetools-1.3.3.dist-info/METADATA
robotsparsetools-1.3.3.dist-info/WHEEL
robotsparsetools-1.3.3.dist-info/entry_points.txt
robotsparsetools-1.3.3.dist-info/top_level.txt
robotsparsetools-1.3.3.dist-info/RECORD
