Metadata-Version: 2.1
Name: robotsparsetools
Version: 1.3.3
Summary: Parse robots.txt
Home-page: https://github.com/mino-38/robotsparsetools
Author: minomushi
Author-email: wngx5451@yahoo.co.jp
License: MIT
Keywords: robots.txt parser
Platform: UNKNOWN
Classifier: Development Status :: 5 - Production/Stable
Classifier: Programming Language :: Python :: 3 :: Only
License-File: LICENSE
